opentelemetry/instrumentation/mcp/__init__.py
opentelemetry/instrumentation/mcp/fastmcp_instrumentation.py
opentelemetry/instrumentation/mcp/instrumentation.py
opentelemetry/instrumentation/mcp/utils.py
opentelemetry/instrumentation/mcp/version.py
opentelemetry_instrumentation_mcp-0.51.1.dist-info/METADATA
opentelemetry_instrumentation_mcp-0.51.1.dist-info/WHEEL
opentelemetry_instrumentation_mcp-0.51.1.dist-info/entry_points.txt
opentelemetry_instrumentation_mcp-0.51.1.dist-info/RECORD
